<annotation>
	<folder>car</folder>
	<filename>car (6).jpg</filename>
	<path>C:\Users\abdur\SUAS COMPETITION\models-master\custom object\images\image data\car\car (6).jpg</path>
	<source>
		<database>Unknown</database>
	</source>
	<size>
		<width>310</width>
		<height>163</height>
		<depth>3</depth>
	</size>
	<segmented>0</segmented>
	<object>
		<name>car</name>
		<pose>Unspecified</pose>
		<truncated>0</truncated>
		<difficult>0</difficult>
		<bndbox>
			<xmin>28</xmin>
			<ymin>73</ymin>
			<xmax>265</xmax>
			<ymax>138</ymax>
		</bndbox>
	</object>
</annotation>
