<annotation>
	<folder>snowboard</folder>
	<filename>snowboard (411).jpg</filename>
	<path>C:\Users\abdur\DENEME\models\research\object_detection\images\image data\snowboard\snowboard (411).jpg</path>
	<source>
		<database>Unknown</database>
	</source>
	<size>
		<width>225</width>
		<height>225</height>
		<depth>3</depth>
	</size>
	<segmented>0</segmented>
	<object>
		<name>snowboard</name>
		<pose>Unspecified</pose>
		<truncated>0</truncated>
		<difficult>0</difficult>
		<bndbox>
			<xmin>39</xmin>
			<ymin>145</ymin>
			<xmax>157</xmax>
			<ymax>188</ymax>
		</bndbox>
	</object>
	<object>
		<name>snowboard</name>
		<pose>Unspecified</pose>
		<truncated>0</truncated>
		<difficult>0</difficult>
		<bndbox>
			<xmin>200</xmin>
			<ymin>149</ymin>
			<xmax>220</xmax>
			<ymax>164</ymax>
		</bndbox>
	</object>
</annotation>
